odoo/addons/stock_picking_report_custom_description/README.rst
odoo/addons/stock_picking_report_custom_description/__init__.py
odoo/addons/stock_picking_report_custom_description/__manifest__.py
odoo/addons/stock_picking_report_custom_description/i18n/es.po
odoo/addons/stock_picking_report_custom_description/i18n/stock_picking_report_custom_description.pot
odoo/addons/stock_picking_report_custom_description/readme/CONTRIBUTORS.rst
odoo/addons/stock_picking_report_custom_description/readme/DESCRIPTION.rst
odoo/addons/stock_picking_report_custom_description/readme/USAGE.rst
odoo/addons/stock_picking_report_custom_description/static/description/icon.png
odoo/addons/stock_picking_report_custom_description/static/description/index.html
odoo/addons/stock_picking_report_custom_description/views/report_deliveryslip.xml
odoo/addons/stock_picking_report_custom_description/views/report_stockpicking_operations.xml
odoo/addons/stock_picking_report_custom_description/views/stock_report.xml
odoo13_addon_stock_picking_report_custom_description-13.0.1.0.1.dev2.dist-info/METADATA
odoo13_addon_stock_picking_report_custom_description-13.0.1.0.1.dev2.dist-info/WHEEL
odoo13_addon_stock_picking_report_custom_description-13.0.1.0.1.dev2.dist-info/top_level.txt
odoo13_addon_stock_picking_report_custom_description-13.0.1.0.1.dev2.dist-info/RECORD
